lzon/__init__.py
lzon/lzon.py
lzon-0.1.1.dist-info/LICENSE
lzon-0.1.1.dist-info/METADATA
lzon-0.1.1.dist-info/WHEEL
lzon-0.1.1.dist-info/RECORD
