Metadata-Version: 2.1
Name: lzon
Version: 0.1.1
Summary: Lazy loading for JSON packets
Home-page: https://gitlab.com/deepadmax/lzon
License: MIT
Author: Maximillian Strand
Author-email: maxi@millian.se
Requires-Python: >=3.9,<4.0
Classifier: License :: OSI Approved :: MIT License
Classifier: Programming Language :: Python :: 3
Classifier: Programming Language :: Python :: 3.9
Classifier: Programming Language :: Python :: 3.10
Classifier: Programming Language :: Python :: 3.11
Project-URL: Repository, https://gitlab.com/deepadmax/lzon
